Metadata-Version: 2.1
Name: kasaya
Version: 0.0.5
Summary: A tool to juice information from URL
Home-page: http://github.com/git-kale/kasaya
Author: Mahesh Kale
Author-email: kalemaheshj@gmail.com
License: MIT
Platform: UNKNOWN
